sqlorm/__init__.py
sqlorm/builder.py
sqlorm/drivers/__init__.py
sqlorm/drivers/mysql.py
sqlorm/drivers/postgresql.py
sqlorm/drivers/sqlite.py
sqlorm/engine.py
sqlorm/helpers.py
sqlorm/mapper.py
sqlorm/migrate.py
sqlorm/model.py
sqlorm/opentelemetry/__init__.py
sqlorm/opentelemetry/tracer.py
sqlorm/resultset.py
sqlorm/schema.py
sqlorm/sql.py
sqlorm/sql_template.py
sqlorm/sqlfunc.py
sqlorm/types/__init__.py
sqlorm/types/encrypted.py
sqlorm_py-0.4.1.dist-info/WHEEL
sqlorm_py-0.4.1.dist-info/entry_points.txt
sqlorm_py-0.4.1.dist-info/METADATA
sqlorm_py-0.4.1.dist-info/RECORD
