Metadata-Version: 2.4
Name: sqlorm-py
Version: 0.4.1
Summary: A new kind or ORM that do not abstract away your database or SQL queries.
Author: Maxime Bouroumeau-Fuseau
Author-email: Maxime Bouroumeau-Fuseau <maxime.bouroumeau@gmail.com>
License-Expression: MIT
Requires-Dist: blinker>=1.9.0
Requires-Python: >=3.10
Project-URL: Repository, https://github.com/hyperflask/sqlorm
